OLS_pipeline/__init__.py
OLS_pipeline/pipeline.py
tests/__init__.py
tests/test_pipeline.py
PanelOLSPipeline-0.1.1.dist-info/LICENSE
PanelOLSPipeline-0.1.1.dist-info/METADATA
PanelOLSPipeline-0.1.1.dist-info/WHEEL
PanelOLSPipeline-0.1.1.dist-info/top_level.txt
PanelOLSPipeline-0.1.1.dist-info/RECORD
