Metadata-Version: 2.1
Name: PanelOLSPipeline
Version: 0.1.1
Summary: A package to preprocess data, fit models, and calculate VIF for Panel Data Regression
Home-page: https://github.com/GrimmXoXo/OLS_package
Author: Gaurav M
Author-email: gaurav.mohindroo9@gmail.com
Classifier: Programming Language :: Python :: 3
Classifier: License :: OSI Approved :: MIT License
Classifier: Operating System :: OS Independent
Requires-Python: >=3.6
License-File: LICENSE
Requires-Dist: pandas
Requires-Dist: statsmodels
Requires-Dist: scikit-learn
Requires-Dist: linearmodels
Requires-Dist: joblib
